<?xml version="1.0" encoding="UTF-8"?>
<ofd:Page xmlns:ofd="http://www.ofdspec.org/2016"><ofd:Area><ofd:PhysicalBox>0 0 210 297</ofd:PhysicalBox></ofd:Area><ofd:Template TemplateID="100"/><ofd:Content><ofd:Layer ID="978"><ofd:TextObject ID="980" Boundary="34 36.95 165 4.85" Font="85" Size="3.175"><ofd:TextCode X="0" Y="2.730055" DeltaX="g 7 3.175">百望股份有限公司</ofd:TextCode></ofd:TextObject><ofd:TextObject ID="981" Boundary="34 44.88 165 4.85" Font="85" Size="3.175"><ofd:TextCode X="0" Y="2.730055" DeltaX="g 4 1.5875 3.175">ukey测试</ofd:TextCode></ofd:TextObject><ofd:TextObject ID="982" Boundary="57 52.06 36 4.84" Font="85" Size="3.175"><ofd:TextCode X="0" Y="2.730055" DeltaX="g 11 1.5875">011002680026</ofd:TextCode></ofd:TextObject><ofd:TextObject ID="983" Boundary="105 52.06 30 4.55" Font="85" Size="3.175"><ofd:TextCode X="0" Y="2.730055" DeltaX="g 7 1.5875">71500013</ofd:TextCode></ofd:TextObject><ofd:TextObject ID="984" Boundary="162.39 275.5 38 4.55" Font="85" Size="3.175"><ofd:TextCode X="0" Y="3.417555" DeltaX="g 4 1.5875 3.175 g 2 1.5875 3.175 g 2 1.5875">2020年02月20日</ofd:TextCode></ofd:TextObject><ofd:TextObject ID="985" Boundary="16.13 267.38 188.05 7.67" Font="85" Size="3.175"><ofd:TextCode X="0" Y="2.730055" DeltaX="g 3 3.175">稻谷交易</ofd:TextCode></ofd:TextObject><ofd:TextObject ID="986" Boundary="4.5 66 7 7" Font="85" Size="3.175"><ofd:TextCode X="1.9125" Y="4.642555" DeltaX="1.5875">79</ofd:TextCode></ofd:TextObject><ofd:TextObject ID="987" Boundary="12.5 66 43 7" Font="85" Size="3.175"><ofd:TextCode X="0" Y="4.642555" DeltaX="1.5875 g 2 3.175 1.5875 3.175">*谷物*稻谷</ofd:TextCode></ofd:TextObject><ofd:TextObject ID="988" Boundary="83.5 66 10 7" Font="85" Size="3.175"><ofd:TextCode X="3.4125" Y="4.642555">克</ofd:TextCode></ofd:TextObject><ofd:TextObject ID="989" Boundary="95.5 66 18 7" Font="85" Size="3.175"><ofd:TextCode X="16.4125" Y="4.642555">1</ofd:TextCode></ofd:TextObject><ofd:TextObject ID="990" Boundary="115.5 66 18 7" Font="85" Size="3.175"><ofd:TextCode X="10.0625" Y="4.642555" DeltaX="g 4 1.5875">97.09</ofd:TextCode></ofd:TextObject><ofd:TextObject ID="991" Boundary="135.5 66 28 7" Font="85" Size="3.175"><ofd:TextCode X="20.0625" Y="4.642555" DeltaX="g 4 1.5875">97.09</ofd:TextCode></ofd:TextObject><ofd:TextObject ID="992" Boundary="165.5 66 9 7" Font="85" Size="3.175"><ofd:TextCode X="5.825" Y="4.642555" DeltaX="1.5875">3%</ofd:TextCode></ofd:TextObject><ofd:TextObject ID="993" Boundary="176.5 66 28 7" Font="85" Size="3.175"><ofd:TextCode X="21.65" Y="4.642555" DeltaX="g 3 1.5875">2.91</ofd:TextCode></ofd:TextObject><ofd:TextObject ID="994" Boundary="4.5 73 7 7" Font="85" Size="3.175"><ofd:TextCode X="1.9125" Y="4.642555" DeltaX="1.5875">80</ofd:TextCode></ofd:TextObject><ofd:TextObject ID="995" Boundary="12.5 73 43 7" Font="85" Size="3.175"><ofd:TextCode X="0" Y="4.642555" DeltaX="1.5875 g 2 3.175 1.5875 3.175">*谷物*稻谷</ofd:TextCode></ofd:TextObject><ofd:TextObject ID="996" Boundary="83.5 73 10 7" Font="85" Size="3.175"><ofd:TextCode X="3.4125" Y="4.642555">克</ofd:TextCode></ofd:TextObject><ofd:TextObject ID="997" Boundary="95.5 73 18 7" Font="85" Size="3.175"><ofd:TextCode X="16.4125" Y="4.642555">1</ofd:TextCode></ofd:TextObject><ofd:TextObject ID="998" Boundary="115.5 73 18 7" Font="85" Size="3.175"><ofd:TextCode X="10.0625" Y="4.642555" DeltaX="g 4 1.5875">97.09</ofd:TextCode></ofd:TextObject><ofd:TextObject ID="999" Boundary="135.5 73 28 7" Font="85" Size="3.175"><ofd:TextCode X="20.0625" Y="4.642555" DeltaX="g 4 1.5875">97.09</ofd:TextCode></ofd:TextObject><ofd:TextObject ID="1000" Boundary="165.5 73 9 7" Font="85" Size="3.175"><ofd:TextCode X="5.825" Y="4.642555" DeltaX="1.5875">3%</ofd:TextCode></ofd:TextObject><ofd:TextObject ID="1001" Boundary="176.5 73 28 7" Font="85" Size="3.175"><ofd:TextCode X="21.65" Y="4.642555" DeltaX="g 3 1.5875">2.91</ofd:TextCode></ofd:TextObject><ofd:TextObject ID="1002" Boundary="4.5 80 7 7" Font="85" Size="3.175"><ofd:TextCode X="1.9125" Y="4.642555" DeltaX="1.5875">81</ofd:TextCode></ofd:TextObject><ofd:TextObject ID="1003" Boundary="12.5 80 43 7" Font="85" Size="3.175"><ofd:TextCode X="0" Y="4.642555" DeltaX="1.5875 g 2 3.175 1.5875 3.175">*谷物*稻谷</ofd:TextCode></ofd:TextObject><ofd:TextObject ID="1004" Boundary="83.5 80 10 7" Font="85" Size="3.175"><ofd:TextCode X="3.4125" Y="4.642555">克</ofd:TextCode></ofd:TextObject><ofd:TextObject ID="1005" Boundary="95.5 80 18 7" Font="85" Size="3.175"><ofd:TextCode X="16.4125" Y="4.642555">1</ofd:TextCode></ofd:TextObject><ofd:TextObject ID="1006" Boundary="115.5 80 18 7" Font="85" Size="3.175"><ofd:TextCode X="10.0625" Y="4.642555" DeltaX="g 4 1.5875">97.09</ofd:TextCode></ofd:TextObject><ofd:TextObject ID="1007" Boundary="135.5 80 28 7" Font="85" Size="3.175"><ofd:TextCode X="20.0625" Y="4.642555" DeltaX="g 4 1.5875">97.09</ofd:TextCode></ofd:TextObject><ofd:TextObject ID="1008" Boundary="165.5 80 9 7" Font="85" Size="3.175"><ofd:TextCode X="5.825" Y="4.642555" DeltaX="1.5875">3%</ofd:TextCode></ofd:TextObject><ofd:TextObject ID="1009" Boundary="176.5 80 28 7" Font="85" Size="3.175"><ofd:TextCode X="21.65" Y="4.642555" DeltaX="g 3 1.5875">2.91</ofd:TextCode></ofd:TextObject><ofd:TextObject ID="1010" Boundary="4.5 87 7 7" Font="85" Size="3.175"><ofd:TextCode X="1.9125" Y="4.642555" DeltaX="1.5875">82</ofd:TextCode></ofd:TextObject><ofd:TextObject ID="1011" Boundary="12.5 87 43 7" Font="85" Size="3.175"><ofd:TextCode X="0" Y="4.642555" DeltaX="1.5875 g 2 3.175 1.5875 3.175">*谷物*稻谷</ofd:TextCode></ofd:TextObject><ofd:TextObject ID="1012" Boundary="83.5 87 10 7" Font="85" Size="3.175"><ofd:TextCode X="3.4125" Y="4.642555">克</ofd:TextCode></ofd:TextObject><ofd:TextObject ID="1013" Boundary="95.5 87 18 7" Font="85" Size="3.175"><ofd:TextCode X="16.4125" Y="4.642555">1</ofd:TextCode></ofd:TextObject><ofd:TextObject ID="1014" Boundary="115.5 87 18 7" Font="85" Size="3.175"><ofd:TextCode X="10.0625" Y="4.642555" DeltaX="g 4 1.5875">97.09</ofd:TextCode></ofd:TextObject><ofd:TextObject ID="1015" Boundary="135.5 87 28 7" Font="85" Size="3.175"><ofd:TextCode X="20.0625" Y="4.642555" DeltaX="g 4 1.5875">97.09</ofd:TextCode></ofd:TextObject><ofd:TextObject ID="1016" Boundary="165.5 87 9 7" Font="85" Size="3.175"><ofd:TextCode X="5.825" Y="4.642555" DeltaX="1.5875">3%</ofd:TextCode></ofd:TextObject><ofd:TextObject ID="1017" Boundary="176.5 87 28 7" Font="85" Size="3.175"><ofd:TextCode X="21.65" Y="4.642555" DeltaX="g 3 1.5875">2.91</ofd:TextCode></ofd:TextObject><ofd:TextObject ID="1018" Boundary="4.5 94 7 7" Font="85" Size="3.175"><ofd:TextCode X="1.9125" Y="4.642555" DeltaX="1.5875">83</ofd:TextCode></ofd:TextObject><ofd:TextObject ID="1019" Boundary="12.5 94 43 7" Font="85" Size="3.175"><ofd:TextCode X="0" Y="4.642555" DeltaX="1.5875 g 2 3.175 1.5875 3.175">*谷物*稻谷</ofd:TextCode></ofd:TextObject><ofd:TextObject ID="1020" Boundary="83.5 94 10 7" Font="85" Size="3.175"><ofd:TextCode X="3.4125" Y="4.642555">克</ofd:TextCode></ofd:TextObject><ofd:TextObject ID="1021" Boundary="95.5 94 18 7" Font="85" Size="3.175"><ofd:TextCode X="16.4125" Y="4.642555">1</ofd:TextCode></ofd:TextObject><ofd:TextObject ID="1022" Boundary="115.5 94 18 7" Font="85" Size="3.175"><ofd:TextCode X="10.0625" Y="4.642555" DeltaX="g 4 1.5875">97.09</ofd:TextCode></ofd:TextObject><ofd:TextObject ID="1023" Boundary="135.5 94 28 7" Font="85" Size="3.175"><ofd:TextCode X="20.0625" Y="4.642555" DeltaX="g 4 1.5875">97.09</ofd:TextCode></ofd:TextObject><ofd:TextObject ID="1024" Boundary="165.5 94 9 7" Font="85" Size="3.175"><ofd:TextCode X="5.825" Y="4.642555" DeltaX="1.5875">3%</ofd:TextCode></ofd:TextObject><ofd:TextObject ID="1025" Boundary="176.5 94 28 7" Font="85" Size="3.175"><ofd:TextCode X="21.65" Y="4.642555" DeltaX="g 3 1.5875">2.91</ofd:TextCode></ofd:TextObject><ofd:TextObject ID="1026" Boundary="4.5 101 7 7" Font="85" Size="3.175"><ofd:TextCode X="1.9125" Y="4.642555" DeltaX="1.5875">84</ofd:TextCode></ofd:TextObject><ofd:TextObject ID="1027" Boundary="12.5 101 43 7" Font="85" Size="3.175"><ofd:TextCode X="0" Y="4.642555" DeltaX="1.5875 g 2 3.175 1.5875 3.175">*谷物*稻谷</ofd:TextCode></ofd:TextObject><ofd:TextObject ID="1028" Boundary="83.5 101 10 7" Font="85" Size="3.175"><ofd:TextCode X="3.4125" Y="4.642555">克</ofd:TextCode></ofd:TextObject><ofd:TextObject ID="1029" Boundary="95.5 101 18 7" Font="85" Size="3.175"><ofd:TextCode X="16.4125" Y="4.642555">1</ofd:TextCode></ofd:TextObject><ofd:TextObject ID="1030" Boundary="115.5 101 18 7" Font="85" Size="3.175"><ofd:TextCode X="10.0625" Y="4.642555" DeltaX="g 4 1.5875">97.09</ofd:TextCode></ofd:TextObject><ofd:TextObject ID="1031" Boundary="135.5 101 28 7" Font="85" Size="3.175"><ofd:TextCode X="20.0625" Y="4.642555" DeltaX="g 4 1.5875">97.09</ofd:TextCode></ofd:TextObject><ofd:TextObject ID="1032" Boundary="165.5 101 9 7" Font="85" Size="3.175"><ofd:TextCode X="5.825" Y="4.642555" DeltaX="1.5875">3%</ofd:TextCode></ofd:TextObject><ofd:TextObject ID="1033" Boundary="176.5 101 28 7" Font="85" Size="3.175"><ofd:TextCode X="21.65" Y="4.642555" DeltaX="g 3 1.5875">2.91</ofd:TextCode></ofd:TextObject><ofd:TextObject ID="1034" Boundary="4.5 108 7 7" Font="85" Size="3.175"><ofd:TextCode X="1.9125" Y="4.642555" DeltaX="1.5875">85</ofd:TextCode></ofd:TextObject><ofd:TextObject ID="1035" Boundary="12.5 108 43 7" Font="85" Size="3.175"><ofd:TextCode X="0" Y="4.642555" DeltaX="1.5875 g 2 3.175 1.5875 3.175">*谷物*稻谷</ofd:TextCode></ofd:TextObject><ofd:TextObject ID="1036" Boundary="83.5 108 10 7" Font="85" Size="3.175"><ofd:TextCode X="3.4125" Y="4.642555">克</ofd:TextCode></ofd:TextObject><ofd:TextObject ID="1037" Boundary="95.5 108 18 7" Font="85" Size="3.175"><ofd:TextCode X="16.4125" Y="4.642555">1</ofd:TextCode></ofd:TextObject><ofd:TextObject ID="1038" Boundary="115.5 108 18 7" Font="85" Size="3.175"><ofd:TextCode X="10.0625" Y="4.642555" DeltaX="g 4 1.5875">97.09</ofd:TextCode></ofd:TextObject><ofd:TextObject ID="1039" Boundary="135.5 108 28 7" Font="85" Size="3.175"><ofd:TextCode X="20.0625" Y="4.642555" DeltaX="g 4 1.5875">97.09</ofd:TextCode></ofd:TextObject><ofd:TextObject ID="1040" Boundary="165.5 108 9 7" Font="85" Size="3.175"><ofd:TextCode X="5.825" Y="4.642555" DeltaX="1.5875">3%</ofd:TextCode></ofd:TextObject><ofd:TextObject ID="1041" Boundary="176.5 108 28 7" Font="85" Size="3.175"><ofd:TextCode X="21.65" Y="4.642555" DeltaX="g 3 1.5875">2.91</ofd:TextCode></ofd:TextObject><ofd:TextObject ID="1042" Boundary="4.5 115 7 7" Font="85" Size="3.175"><ofd:TextCode X="1.9125" Y="4.642555" DeltaX="1.5875">86</ofd:TextCode></ofd:TextObject><ofd:TextObject ID="1043" Boundary="12.5 115 43 7" Font="85" Size="3.175"><ofd:TextCode X="0" Y="4.642555" DeltaX="1.5875 g 2 3.175 1.5875 3.175">*谷物*稻谷</ofd:TextCode></ofd:TextObject><ofd:TextObject ID="1044" Boundary="83.5 115 10 7" Font="85" Size="3.175"><ofd:TextCode X="3.4125" Y="4.642555">克</ofd:TextCode></ofd:TextObject><ofd:TextObject ID="1045" Boundary="95.5 115 18 7" Font="85" Size="3.175"><ofd:TextCode X="16.4125" Y="4.642555">1</ofd:TextCode></ofd:TextObject><ofd:TextObject ID="1046" Boundary="115.5 115 18 7" Font="85" Size="3.175"><ofd:TextCode X="10.0625" Y="4.642555" DeltaX="g 4 1.5875">97.09</ofd:TextCode></ofd:TextObject><ofd:TextObject ID="1047" Boundary="135.5 115 28 7" Font="85" Size="3.175"><ofd:TextCode X="20.0625" Y="4.642555" DeltaX="g 4 1.5875">97.09</ofd:TextCode></ofd:TextObject><ofd:TextObject ID="1048" Boundary="165.5 115 9 7" Font="85" Size="3.175"><ofd:TextCode X="5.825" Y="4.642555" DeltaX="1.5875">3%</ofd:TextCode></ofd:TextObject><ofd:TextObject ID="1049" Boundary="176.5 115 28 7" Font="85" Size="3.175"><ofd:TextCode X="21.65" Y="4.642555" DeltaX="g 3 1.5875">2.91</ofd:TextCode></ofd:TextObject><ofd:TextObject ID="1050" Boundary="4.5 122 7 7" Font="85" Size="3.175"><ofd:TextCode X="1.9125" Y="4.642555" DeltaX="1.5875">87</ofd:TextCode></ofd:TextObject><ofd:TextObject ID="1051" Boundary="12.5 122 43 7" Font="85" Size="3.175"><ofd:TextCode X="0" Y="4.642555" DeltaX="1.5875 g 2 3.175 1.5875 3.175">*谷物*稻谷</ofd:TextCode></ofd:TextObject><ofd:TextObject ID="1052" Boundary="83.5 122 10 7" Font="85" Size="3.175"><ofd:TextCode X="3.4125" Y="4.642555">克</ofd:TextCode></ofd:TextObject><ofd:TextObject ID="1053" Boundary="95.5 122 18 7" Font="85" Size="3.175"><ofd:TextCode X="16.4125" Y="4.642555">1</ofd:TextCode></ofd:TextObject><ofd:TextObject ID="1054" Boundary="115.5 122 18 7" Font="85" Size="3.175"><ofd:TextCode X="10.0625" Y="4.642555" DeltaX="g 4 1.5875">97.09</ofd:TextCode></ofd:TextObject><ofd:TextObject ID="1055" Boundary="135.5 122 28 7" Font="85" Size="3.175"><ofd:TextCode X="20.0625" Y="4.642555" DeltaX="g 4 1.5875">97.09</ofd:TextCode></ofd:TextObject><ofd:TextObject ID="1056" Boundary="165.5 122 9 7" Font="85" Size="3.175"><ofd:TextCode X="5.825" Y="4.642555" DeltaX="1.5875">3%</ofd:TextCode></ofd:TextObject><ofd:TextObject ID="1057" Boundary="176.5 122 28 7" Font="85" Size="3.175"><ofd:TextCode X="21.65" Y="4.642555" DeltaX="g 3 1.5875">2.91</ofd:TextCode></ofd:TextObject><ofd:TextObject ID="1058" Boundary="4.5 129 7 7" Font="85" Size="3.175"><ofd:TextCode X="1.9125" Y="4.642555" DeltaX="1.5875">88</ofd:TextCode></ofd:TextObject><ofd:TextObject ID="1059" Boundary="12.5 129 43 7" Font="85" Size="3.175"><ofd:TextCode X="0" Y="4.642555" DeltaX="1.5875 g 2 3.175 1.5875 3.175">*谷物*稻谷</ofd:TextCode></ofd:TextObject><ofd:TextObject ID="1060" Boundary="83.5 129 10 7" Font="85" Size="3.175"><ofd:TextCode X="3.4125" Y="4.642555">克</ofd:TextCode></ofd:TextObject><ofd:TextObject ID="1061" Boundary="95.5 129 18 7" Font="85" Size="3.175"><ofd:TextCode X="16.4125" Y="4.642555">1</ofd:TextCode></ofd:TextObject><ofd:TextObject ID="1062" Boundary="115.5 129 18 7" Font="85" Size="3.175"><ofd:TextCode X="10.0625" Y="4.642555" DeltaX="g 4 1.5875">97.09</ofd:TextCode></ofd:TextObject><ofd:TextObject ID="1063" Boundary="135.5 129 28 7" Font="85" Size="3.175"><ofd:TextCode X="20.0625" Y="4.642555" DeltaX="g 4 1.5875">97.09</ofd:TextCode></ofd:TextObject><ofd:TextObject ID="1064" Boundary="165.5 129 9 7" Font="85" Size="3.175"><ofd:TextCode X="5.825" Y="4.642555" DeltaX="1.5875">3%</ofd:TextCode></ofd:TextObject><ofd:TextObject ID="1065" Boundary="176.5 129 28 7" Font="85" Size="3.175"><ofd:TextCode X="21.65" Y="4.642555" DeltaX="g 3 1.5875">2.91</ofd:TextCode></ofd:TextObject><ofd:TextObject ID="1066" Boundary="4.5 136 7 7" Font="85" Size="3.175"><ofd:TextCode X="1.9125" Y="4.642555" DeltaX="1.5875">89</ofd:TextCode></ofd:TextObject><ofd:TextObject ID="1067" Boundary="12.5 136 43 7" Font="85" Size="3.175"><ofd:TextCode X="0" Y="4.642555" DeltaX="1.5875 g 2 3.175 1.5875 3.175">*谷物*稻谷</ofd:TextCode></ofd:TextObject><ofd:TextObject ID="1068" Boundary="83.5 136 10 7" Font="85" Size="3.175"><ofd:TextCode X="3.4125" Y="4.642555">克</ofd:TextCode></ofd:TextObject><ofd:TextObject ID="1069" Boundary="95.5 136 18 7" Font="85" Size="3.175"><ofd:TextCode X="16.4125" Y="4.642555">1</ofd:TextCode></ofd:TextObject><ofd:TextObject ID="1070" Boundary="115.5 136 18 7" Font="85" Size="3.175"><ofd:TextCode X="10.0625" Y="4.642555" DeltaX="g 4 1.5875">97.09</ofd:TextCode></ofd:TextObject><ofd:TextObject ID="1071" Boundary="135.5 136 28 7" Font="85" Size="3.175"><ofd:TextCode X="20.0625" Y="4.642555" DeltaX="g 4 1.5875">97.09</ofd:TextCode></ofd:TextObject><ofd:TextObject ID="1072" Boundary="165.5 136 9 7" Font="85" Size="3.175"><ofd:TextCode X="5.825" Y="4.642555" DeltaX="1.5875">3%</ofd:TextCode></ofd:TextObject><ofd:TextObject ID="1073" Boundary="176.5 136 28 7" Font="85" Size="3.175"><ofd:TextCode X="21.65" Y="4.642555" DeltaX="g 3 1.5875">2.91</ofd:TextCode></ofd:TextObject><ofd:TextObject ID="1074" Boundary="4.5 143 7 7" Font="85" Size="3.175"><ofd:TextCode X="1.9125" Y="4.642555" DeltaX="1.5875">90</ofd:TextCode></ofd:TextObject><ofd:TextObject ID="1075" Boundary="12.5 143 43 7" Font="85" Size="3.175"><ofd:TextCode X="0" Y="4.642555" DeltaX="1.5875 g 2 3.175 1.5875 3.175">*谷物*稻谷</ofd:TextCode></ofd:TextObject><ofd:TextObject ID="1076" Boundary="83.5 143 10 7" Font="85" Size="3.175"><ofd:TextCode X="3.4125" Y="4.642555">克</ofd:TextCode></ofd:TextObject><ofd:TextObject ID="1077" Boundary="95.5 143 18 7" Font="85" Size="3.175"><ofd:TextCode X="16.4125" Y="4.642555">1</ofd:TextCode></ofd:TextObject><ofd:TextObject ID="1078" Boundary="115.5 143 18 7" Font="85" Size="3.175"><ofd:TextCode X="10.0625" Y="4.642555" DeltaX="g 4 1.5875">97.09</ofd:TextCode></ofd:TextObject><ofd:TextObject ID="1079" Boundary="135.5 143 28 7" Font="85" Size="3.175"><ofd:TextCode X="20.0625" Y="4.642555" DeltaX="g 4 1.5875">97.09</ofd:TextCode></ofd:TextObject><ofd:TextObject ID="1080" Boundary="165.5 143 9 7" Font="85" Size="3.175"><ofd:TextCode X="5.825" Y="4.642555" DeltaX="1.5875">3%</ofd:TextCode></ofd:TextObject><ofd:TextObject ID="1081" Boundary="176.5 143 28 7" Font="85" Size="3.175"><ofd:TextCode X="21.65" Y="4.642555" DeltaX="g 3 1.5875">2.91</ofd:TextCode></ofd:TextObject><ofd:TextObject ID="1082" Boundary="4.5 150 7 7" Font="85" Size="3.175"><ofd:TextCode X="1.9125" Y="4.642555" DeltaX="1.5875">91</ofd:TextCode></ofd:TextObject><ofd:TextObject ID="1083" Boundary="12.5 150 43 7" Font="85" Size="3.175"><ofd:TextCode X="0" Y="4.642555" DeltaX="1.5875 g 2 3.175 1.5875 3.175">*谷物*稻谷</ofd:TextCode></ofd:TextObject><ofd:TextObject ID="1084" Boundary="83.5 150 10 7" Font="85" Size="3.175"><ofd:TextCode X="3.4125" Y="4.642555">克</ofd:TextCode></ofd:TextObject><ofd:TextObject ID="1085" Boundary="95.5 150 18 7" Font="85" Size="3.175"><ofd:TextCode X="16.4125" Y="4.642555">1</ofd:TextCode></ofd:TextObject><ofd:TextObject ID="1086" Boundary="115.5 150 18 7" Font="85" Size="3.175"><ofd:TextCode X="10.0625" Y="4.642555" DeltaX="g 4 1.5875">97.09</ofd:TextCode></ofd:TextObject><ofd:TextObject ID="1087" Boundary="135.5 150 28 7" Font="85" Size="3.175"><ofd:TextCode X="20.0625" Y="4.642555" DeltaX="g 4 1.5875">97.09</ofd:TextCode></ofd:TextObject><ofd:TextObject ID="1088" Boundary="165.5 150 9 7" Font="85" Size="3.175"><ofd:TextCode X="5.825" Y="4.642555" DeltaX="1.5875">3%</ofd:TextCode></ofd:TextObject><ofd:TextObject ID="1089" Boundary="176.5 150 28 7" Font="85" Size="3.175"><ofd:TextCode X="21.65" Y="4.642555" DeltaX="g 3 1.5875">2.91</ofd:TextCode></ofd:TextObject><ofd:TextObject ID="1090" Boundary="4.5 157 7 7" Font="85" Size="3.175"><ofd:TextCode X="1.9125" Y="4.642555" DeltaX="1.5875">92</ofd:TextCode></ofd:TextObject><ofd:TextObject ID="1091" Boundary="12.5 157 43 7" Font="85" Size="3.175"><ofd:TextCode X="0" Y="4.642555" DeltaX="1.5875 g 2 3.175 1.5875 3.175">*谷物*稻谷</ofd:TextCode></ofd:TextObject><ofd:TextObject ID="1092" Boundary="83.5 157 10 7" Font="85" Size="3.175"><ofd:TextCode X="3.4125" Y="4.642555">克</ofd:TextCode></ofd:TextObject><ofd:TextObject ID="1093" Boundary="95.5 157 18 7" Font="85" Size="3.175"><ofd:TextCode X="16.4125" Y="4.642555">1</ofd:TextCode></ofd:TextObject><ofd:TextObject ID="1094" Boundary="115.5 157 18 7" Font="85" Size="3.175"><ofd:TextCode X="10.0625" Y="4.642555" DeltaX="g 4 1.5875">97.09</ofd:TextCode></ofd:TextObject><ofd:TextObject ID="1095" Boundary="135.5 157 28 7" Font="85" Size="3.175"><ofd:TextCode X="20.0625" Y="4.642555" DeltaX="g 4 1.5875">97.09</ofd:TextCode></ofd:TextObject><ofd:TextObject ID="1096" Boundary="165.5 157 9 7" Font="85" Size="3.175"><ofd:TextCode X="5.825" Y="4.642555" DeltaX="1.5875">3%</ofd:TextCode></ofd:TextObject><ofd:TextObject ID="1097" Boundary="176.5 157 28 7" Font="85" Size="3.175"><ofd:TextCode X="21.65" Y="4.642555" DeltaX="g 3 1.5875">2.91</ofd:TextCode></ofd:TextObject><ofd:TextObject ID="1098" Boundary="4.5 164 7 7" Font="85" Size="3.175"><ofd:TextCode X="1.9125" Y="4.642555" DeltaX="1.5875">93</ofd:TextCode></ofd:TextObject><ofd:TextObject ID="1099" Boundary="12.5 164 43 7" Font="85" Size="3.175"><ofd:TextCode X="0" Y="4.642555" DeltaX="1.5875 g 2 3.175 1.5875 3.175">*谷物*稻谷</ofd:TextCode></ofd:TextObject><ofd:TextObject ID="1100" Boundary="83.5 164 10 7" Font="85" Size="3.175"><ofd:TextCode X="3.4125" Y="4.642555">克</ofd:TextCode></ofd:TextObject><ofd:TextObject ID="1101" Boundary="95.5 164 18 7" Font="85" Size="3.175"><ofd:TextCode X="16.4125" Y="4.642555">1</ofd:TextCode></ofd:TextObject><ofd:TextObject ID="1102" Boundary="115.5 164 18 7" Font="85" Size="3.175"><ofd:TextCode X="10.0625" Y="4.642555" DeltaX="g 4 1.5875">97.09</ofd:TextCode></ofd:TextObject><ofd:TextObject ID="1103" Boundary="135.5 164 28 7" Font="85" Size="3.175"><ofd:TextCode X="20.0625" Y="4.642555" DeltaX="g 4 1.5875">97.09</ofd:TextCode></ofd:TextObject><ofd:TextObject ID="1104" Boundary="165.5 164 9 7" Font="85" Size="3.175"><ofd:TextCode X="5.825" Y="4.642555" DeltaX="1.5875">3%</ofd:TextCode></ofd:TextObject><ofd:TextObject ID="1105" Boundary="176.5 164 28 7" Font="85" Size="3.175"><ofd:TextCode X="21.65" Y="4.642555" DeltaX="g 3 1.5875">2.91</ofd:TextCode></ofd:TextObject><ofd:TextObject ID="1106" Boundary="4.5 171 7 7" Font="85" Size="3.175"><ofd:TextCode X="1.9125" Y="4.642555" DeltaX="1.5875">94</ofd:TextCode></ofd:TextObject><ofd:TextObject ID="1107" Boundary="12.5 171 43 7" Font="85" Size="3.175"><ofd:TextCode X="0" Y="4.642555" DeltaX="1.5875 g 2 3.175 1.5875 3.175">*谷物*稻谷</ofd:TextCode></ofd:TextObject><ofd:TextObject ID="1108" Boundary="83.5 171 10 7" Font="85" Size="3.175"><ofd:TextCode X="3.4125" Y="4.642555">克</ofd:TextCode></ofd:TextObject><ofd:TextObject ID="1109" Boundary="95.5 171 18 7" Font="85" Size="3.175"><ofd:TextCode X="16.4125" Y="4.642555">1</ofd:TextCode></ofd:TextObject><ofd:TextObject ID="1110" Boundary="115.5 171 18 7" Font="85" Size="3.175"><ofd:TextCode X="10.0625" Y="4.642555" DeltaX="g 4 1.5875">97.09</ofd:TextCode></ofd:TextObject><ofd:TextObject ID="1111" Boundary="135.5 171 28 7" Font="85" Size="3.175"><ofd:TextCode X="20.0625" Y="4.642555" DeltaX="g 4 1.5875">97.09</ofd:TextCode></ofd:TextObject><ofd:TextObject ID="1112" Boundary="165.5 171 9 7" Font="85" Size="3.175"><ofd:TextCode X="5.825" Y="4.642555" DeltaX="1.5875">3%</ofd:TextCode></ofd:TextObject><ofd:TextObject ID="1113" Boundary="176.5 171 28 7" Font="85" Size="3.175"><ofd:TextCode X="21.65" Y="4.642555" DeltaX="g 3 1.5875">2.91</ofd:TextCode></ofd:TextObject><ofd:TextObject ID="1114" Boundary="4.5 178 7 7" Font="85" Size="3.175"><ofd:TextCode X="1.9125" Y="4.642555" DeltaX="1.5875">95</ofd:TextCode></ofd:TextObject><ofd:TextObject ID="1115" Boundary="12.5 178 43 7" Font="85" Size="3.175"><ofd:TextCode X="0" Y="4.642555" DeltaX="1.5875 g 2 3.175 1.5875 3.175">*谷物*稻谷</ofd:TextCode></ofd:TextObject><ofd:TextObject ID="1116" Boundary="83.5 178 10 7" Font="85" Size="3.175"><ofd:TextCode X="3.4125" Y="4.642555">克</ofd:TextCode></ofd:TextObject><ofd:TextObject ID="1117" Boundary="95.5 178 18 7" Font="85" Size="3.175"><ofd:TextCode X="16.4125" Y="4.642555">1</ofd:TextCode></ofd:TextObject><ofd:TextObject ID="1118" Boundary="115.5 178 18 7" Font="85" Size="3.175"><ofd:TextCode X="10.0625" Y="4.642555" DeltaX="g 4 1.5875">97.09</ofd:TextCode></ofd:TextObject><ofd:TextObject ID="1119" Boundary="135.5 178 28 7" Font="85" Size="3.175"><ofd:TextCode X="20.0625" Y="4.642555" DeltaX="g 4 1.5875">97.09</ofd:TextCode></ofd:TextObject><ofd:TextObject ID="1120" Boundary="165.5 178 9 7" Font="85" Size="3.175"><ofd:TextCode X="5.825" Y="4.642555" DeltaX="1.5875">3%</ofd:TextCode></ofd:TextObject><ofd:TextObject ID="1121" Boundary="176.5 178 28 7" Font="85" Size="3.175"><ofd:TextCode X="21.65" Y="4.642555" DeltaX="g 3 1.5875">2.91</ofd:TextCode></ofd:TextObject><ofd:TextObject ID="1122" Boundary="4.5 185 7 7" Font="85" Size="3.175"><ofd:TextCode X="1.9125" Y="4.642555" DeltaX="1.5875">96</ofd:TextCode></ofd:TextObject><ofd:TextObject ID="1123" Boundary="12.5 185 43 7" Font="85" Size="3.175"><ofd:TextCode X="0" Y="4.642555" DeltaX="1.5875 g 2 3.175 1.5875 3.175">*谷物*稻谷</ofd:TextCode></ofd:TextObject><ofd:TextObject ID="1124" Boundary="83.5 185 10 7" Font="85" Size="3.175"><ofd:TextCode X="3.4125" Y="4.642555">克</ofd:TextCode></ofd:TextObject><ofd:TextObject ID="1125" Boundary="95.5 185 18 7" Font="85" Size="3.175"><ofd:TextCode X="16.4125" Y="4.642555">1</ofd:TextCode></ofd:TextObject><ofd:TextObject ID="1126" Boundary="115.5 185 18 7" Font="85" Size="3.175"><ofd:TextCode X="10.0625" Y="4.642555" DeltaX="g 4 1.5875">97.09</ofd:TextCode></ofd:TextObject><ofd:TextObject ID="1127" Boundary="135.5 185 28 7" Font="85" Size="3.175"><ofd:TextCode X="20.0625" Y="4.642555" DeltaX="g 4 1.5875">97.09</ofd:TextCode></ofd:TextObject><ofd:TextObject ID="1128" Boundary="165.5 185 9 7" Font="85" Size="3.175"><ofd:TextCode X="5.825" Y="4.642555" DeltaX="1.5875">3%</ofd:TextCode></ofd:TextObject><ofd:TextObject ID="1129" Boundary="176.5 185 28 7" Font="85" Size="3.175"><ofd:TextCode X="21.65" Y="4.642555" DeltaX="g 3 1.5875">2.91</ofd:TextCode></ofd:TextObject><ofd:TextObject ID="1130" Boundary="4.5 192 7 7" Font="85" Size="3.175"><ofd:TextCode X="1.9125" Y="4.642555" DeltaX="1.5875">97</ofd:TextCode></ofd:TextObject><ofd:TextObject ID="1131" Boundary="12.5 192 43 7" Font="85" Size="3.175"><ofd:TextCode X="0" Y="4.642555" DeltaX="1.5875 g 2 3.175 1.5875 3.175">*谷物*稻谷</ofd:TextCode></ofd:TextObject><ofd:TextObject ID="1132" Boundary="83.5 192 10 7" Font="85" Size="3.175"><ofd:TextCode X="3.4125" Y="4.642555">克</ofd:TextCode></ofd:TextObject><ofd:TextObject ID="1133" Boundary="95.5 192 18 7" Font="85" Size="3.175"><ofd:TextCode X="16.4125" Y="4.642555">1</ofd:TextCode></ofd:TextObject><ofd:TextObject ID="1134" Boundary="115.5 192 18 7" Font="85" Size="3.175"><ofd:TextCode X="10.0625" Y="4.642555" DeltaX="g 4 1.5875">97.09</ofd:TextCode></ofd:TextObject><ofd:TextObject ID="1135" Boundary="135.5 192 28 7" Font="85" Size="3.175"><ofd:TextCode X="20.0625" Y="4.642555" DeltaX="g 4 1.5875">97.09</ofd:TextCode></ofd:TextObject><ofd:TextObject ID="1136" Boundary="165.5 192 9 7" Font="85" Size="3.175"><ofd:TextCode X="5.825" Y="4.642555" DeltaX="1.5875">3%</ofd:TextCode></ofd:TextObject><ofd:TextObject ID="1137" Boundary="176.5 192 28 7" Font="85" Size="3.175"><ofd:TextCode X="21.65" Y="4.642555" DeltaX="g 3 1.5875">2.91</ofd:TextCode></ofd:TextObject><ofd:TextObject ID="1138" Boundary="4.5 199 7 7" Font="85" Size="3.175"><ofd:TextCode X="1.9125" Y="4.642555" DeltaX="1.5875">98</ofd:TextCode></ofd:TextObject><ofd:TextObject ID="1139" Boundary="12.5 199 43 7" Font="85" Size="3.175"><ofd:TextCode X="0" Y="4.642555" DeltaX="1.5875 g 2 3.175 1.5875 3.175">*谷物*稻谷</ofd:TextCode></ofd:TextObject><ofd:TextObject ID="1140" Boundary="83.5 199 10 7" Font="85" Size="3.175"><ofd:TextCode X="3.4125" Y="4.642555">克</ofd:TextCode></ofd:TextObject><ofd:TextObject ID="1141" Boundary="95.5 199 18 7" Font="85" Size="3.175"><ofd:TextCode X="16.4125" Y="4.642555">1</ofd:TextCode></ofd:TextObject><ofd:TextObject ID="1142" Boundary="115.5 199 18 7" Font="85" Size="3.175"><ofd:TextCode X="10.0625" Y="4.642555" DeltaX="g 4 1.5875">97.09</ofd:TextCode></ofd:TextObject><ofd:TextObject ID="1143" Boundary="135.5 199 28 7" Font="85" Size="3.175"><ofd:TextCode X="20.0625" Y="4.642555" DeltaX="g 4 1.5875">97.09</ofd:TextCode></ofd:TextObject><ofd:TextObject ID="1144" Boundary="165.5 199 9 7" Font="85" Size="3.175"><ofd:TextCode X="5.825" Y="4.642555" DeltaX="1.5875">3%</ofd:TextCode></ofd:TextObject><ofd:TextObject ID="1145" Boundary="176.5 199 28 7" Font="85" Size="3.175"><ofd:TextCode X="21.65" Y="4.642555" DeltaX="g 3 1.5875">2.91</ofd:TextCode></ofd:TextObject><ofd:TextObject ID="1146" Boundary="4.5 206 7 7" Font="85" Size="3.175"><ofd:TextCode X="1.9125" Y="4.642555" DeltaX="1.5875">99</ofd:TextCode></ofd:TextObject><ofd:TextObject ID="1147" Boundary="12.5 206 43 7" Font="85" Size="3.175"><ofd:TextCode X="0" Y="4.642555" DeltaX="1.5875 g 2 3.175 1.5875 3.175">*谷物*稻谷</ofd:TextCode></ofd:TextObject><ofd:TextObject ID="1148" Boundary="83.5 206 10 7" Font="85" Size="3.175"><ofd:TextCode X="3.4125" Y="4.642555">克</ofd:TextCode></ofd:TextObject><ofd:TextObject ID="1149" Boundary="95.5 206 18 7" Font="85" Size="3.175"><ofd:TextCode X="16.4125" Y="4.642555">1</ofd:TextCode></ofd:TextObject><ofd:TextObject ID="1150" Boundary="115.5 206 18 7" Font="85" Size="3.175"><ofd:TextCode X="10.0625" Y="4.642555" DeltaX="g 4 1.5875">97.09</ofd:TextCode></ofd:TextObject><ofd:TextObject ID="1151" Boundary="135.5 206 28 7" Font="85" Size="3.175"><ofd:TextCode X="20.0625" Y="4.642555" DeltaX="g 4 1.5875">97.09</ofd:TextCode></ofd:TextObject><ofd:TextObject ID="1152" Boundary="165.5 206 9 7" Font="85" Size="3.175"><ofd:TextCode X="5.825" Y="4.642555" DeltaX="1.5875">3%</ofd:TextCode></ofd:TextObject><ofd:TextObject ID="1153" Boundary="176.5 206 28 7" Font="85" Size="3.175"><ofd:TextCode X="21.65" Y="4.642555" DeltaX="g 3 1.5875">2.91</ofd:TextCode></ofd:TextObject><ofd:TextObject ID="1154" Boundary="4.5 213 7 7" Font="85" Size="3.175"><ofd:TextCode X="1.11875" Y="4.642555" DeltaX="g 2 1.5875">100</ofd:TextCode></ofd:TextObject><ofd:TextObject ID="1155" Boundary="12.5 213 43 7" Font="85" Size="3.175"><ofd:TextCode X="0" Y="4.642555" DeltaX="1.5875 g 2 3.175 1.5875 3.175">*谷物*稻谷</ofd:TextCode></ofd:TextObject><ofd:TextObject ID="1156" Boundary="83.5 213 10 7" Font="85" Size="3.175"><ofd:TextCode X="3.4125" Y="4.642555">克</ofd:TextCode></ofd:TextObject><ofd:TextObject ID="1157" Boundary="95.5 213 18 7" Font="85" Size="3.175"><ofd:TextCode X="16.4125" Y="4.642555">1</ofd:TextCode></ofd:TextObject><ofd:TextObject ID="1158" Boundary="115.5 213 18 7" Font="85" Size="3.175"><ofd:TextCode X="10.0625" Y="4.642555" DeltaX="g 4 1.5875">97.09</ofd:TextCode></ofd:TextObject><ofd:TextObject ID="1159" Boundary="135.5 213 28 7" Font="85" Size="3.175"><ofd:TextCode X="20.0625" Y="4.642555" DeltaX="g 4 1.5875">97.09</ofd:TextCode></ofd:TextObject><ofd:TextObject ID="1160" Boundary="165.5 213 9 7" Font="85" Size="3.175"><ofd:TextCode X="5.825" Y="4.642555" DeltaX="1.5875">3%</ofd:TextCode></ofd:TextObject><ofd:TextObject ID="1161" Boundary="176.5 213 28 7" Font="85" Size="3.175"><ofd:TextCode X="21.65" Y="4.642555" DeltaX="g 3 1.5875">2.91</ofd:TextCode></ofd:TextObject><ofd:TextObject ID="1165" Boundary="170.06 51.95 60 4.84" Font="85" Size="3.175"><ofd:TextCode X="0" Y="2.730055" DeltaX="g 15 1.5875">  4            4</ofd:TextCode></ofd:TextObject><ofd:TextObject ID="1172" Boundary="4.5 246 7 7" Font="28" Size="3.175"><ofd:TextCode X="0.325" Y="4.642555" DeltaX="3.175">小计</ofd:TextCode></ofd:TextObject><ofd:TextObject ID="1173" Boundary="4.5 253 7 7" Font="28" Size="3.175"><ofd:TextCode X="0.325" Y="4.642555" DeltaX="3.175">折扣</ofd:TextCode></ofd:TextObject><ofd:TextObject ID="1174" Boundary="4.5 260 7 7" Font="28" Size="3.175"><ofd:TextCode X="0.325" Y="4.642555" DeltaX="3.175">总计</ofd:TextCode></ofd:TextObject><ofd:TextObject ID="1175" Boundary="135.5 260 28 7" Font="88" Size="3.175"><ofd:TextCode X="12.76" Y="4.47219" DeltaX="g 7 1.905">¥9709.00</ofd:TextCode></ofd:TextObject><ofd:TextObject ID="1176" Boundary="176.5 260 28 7" Font="88" Size="3.175"><ofd:TextCode X="14.665" Y="4.47219" DeltaX="g 6 1.905">¥291.00</ofd:TextCode></ofd:TextObject><ofd:TextObject ID="1183" Boundary="135.5 246 28 7" Font="88" Size="3.175"><ofd:TextCode X="12.76" Y="4.47219" DeltaX="g 7 1.905">¥2135.98</ofd:TextCode></ofd:TextObject><ofd:TextObject ID="1184" Boundary="176.5 246 28 7" Font="88" Size="3.175"><ofd:TextCode X="16.57" Y="4.47219" DeltaX="g 5 1.905">¥64.02</ofd:TextCode></ofd:TextObject></ofd:Layer></ofd:Content></ofd:Page>
